README.rst
pp_vlan.py
pp_vpn.py
setup.py
python_ppvlan.egg-info/PKG-INFO
python_ppvlan.egg-info/SOURCES.txt
python_ppvlan.egg-info/dependency_links.txt
python_ppvlan.egg-info/entry_points.txt
python_ppvlan.egg-info/requires.txt
python_ppvlan.egg-info/top_level.txt